symusic/__init__.py
symusic/core.cpython-313-x86_64-linux-musl.so
symusic/core.pyi
symusic/factory.py
symusic/py.typed
symusic/soundfont.py
symusic/types.py
symusic/bin/abc2midi
symusic/bin/midi2abc
symusic-0.5.9.dist-info/METADATA
symusic-0.5.9.dist-info/WHEEL
symusic-0.5.9.dist-info/RECORD
symusic-0.5.9.dist-info/licenses/LICENSE
