Metadata-Version: 2.2
Name: symusic
Version: 0.5.9
Summary: A high performance MIDI file parser with comprehensible interface.
Keywords: midi,music,mir
Author: Nathan Fradet
Author-Email: Yikai Liao <lyk-boya@outlook.com>, Zhongqi Luo <luozhongqi@mail.com>
Maintainer: Nathan Fradet
Maintainer-Email: Yikai Liao <lyk-boya@outlook.com>, Zhongqi Luo <luozhongqi@mail.com>
License: MIT License
Classifier: Development Status :: 3 - Alpha
Classifier: Programming Language :: C++
Classifier: Programming Language :: Python
Classifier: Intended Audience :: Developers
Classifier: Intended Audience :: Science/Research
Classifier: Topic :: File Formats
Classifier: Topic :: Multimedia :: Sound/Audio :: MIDI
Classifier: License :: OSI Approved :: MIT License
Classifier: Programming Language :: Python :: 3 :: Only
Classifier: Programming Language :: Python :: 3.8
Classifier: Programming Language :: Python :: 3.9
Classifier: Programming Language :: Python :: 3.10
Classifier: Programming Language :: Python :: 3.11
Classifier: Programming Language :: Python :: 3.12
Classifier: Operating System :: MacOS
Classifier: Operating System :: Microsoft :: Windows
Classifier: Operating System :: POSIX
Classifier: Operating System :: Unix
Project-URL: Homepage, https://github.com/Yikai-Liao/symusic
Project-URL: Repository, https://github.com/Yikai-Liao/symusic.git
Project-URL: Issues, https://github.com/Yikai-Liao/symusic/issues
Requires-Python: >=3.8
Requires-Dist: numpy
Requires-Dist: typing_extensions; python_version < "3.8"
Requires-Dist: pySmartDL
Requires-Dist: platformdirs
Provides-Extra: test
Requires-Dist: pytest-cov; extra == "test"
Requires-Dist: pytest-xdist[psutil]; extra == "test"
